mypylogger/__init__.py
mypylogger/config.py
mypylogger/core.py
mypylogger/formatters.py
mypylogger/handlers.py
mypylogger-0.1.5.dist-info/licenses/LICENSE
mypylogger-0.1.5.dist-info/METADATA
mypylogger-0.1.5.dist-info/WHEEL
mypylogger-0.1.5.dist-info/top_level.txt
mypylogger-0.1.5.dist-info/RECORD
