Metadata-Version: 2.4
Name: mypylogger
Version: 0.1.5
Summary: Production-ready Python logging library with structured JSON output, environment-driven configuration, and real-time development support
Author-email: Stephen Abbot <stub@bittikens.com>
License: MIT
Project-URL: Homepage, https://github.com/stabbotco1/mypylogger
Project-URL: Repository, https://github.com/stabbotco1/mypylogger
Project-URL: Documentation, https://github.com/stabbotco1/mypylogger#readme
Project-URL: Bug Tracker, https://github.com/stabbotco1/mypylogger/issues
Project-URL: Security, https://github.com/stabbotco1/mypylogger/blob/main/VULNERABILITIES.md
Keywords: logging,json,structured-logging,python,production,environment-config
Classifier: Development Status :: 3 - Alpha
Classifier: Intended Audience :: Developers
Classifier: Intended Audience :: System Administrators
Classifier: Operating System :: OS Independent
Classifier: Programming Language :: Python :: 3
Classifier: Programming Language :: Python :: 3.8
Classifier: Programming Language :: Python :: 3.9
Classifier: Programming Language :: Python :: 3.10
Classifier: Programming Language :: Python :: 3.11
Classifier: Programming Language :: Python :: 3.12
Classifier: Topic :: Software Development :: Libraries :: Python Modules
Classifier: Topic :: System :: Logging
Classifier: Topic :: System :: Systems Administration
Classifier: Typing :: Typed
Requires-Python: >=3.8
License-File: LICENSE
Requires-Dist: python-json-logger>=2.0.0
Provides-Extra: dev
Requires-Dist: pytest>=7.0.0; extra == "dev"
Requires-Dist: pytest-cov>=4.0.0; extra == "dev"
Requires-Dist: pytest-watch>=4.2.0; extra == "dev"
Requires-Dist: black>=23.0.0; extra == "dev"
Requires-Dist: isort>=5.12.0; extra == "dev"
Requires-Dist: flake8>=6.0.0; extra == "dev"
Requires-Dist: mypy>=1.0.0; extra == "dev"
Requires-Dist: bandit>=1.7.0; extra == "dev"
Requires-Dist: pip-audit>=2.6.0; extra == "dev"
Requires-Dist: pre-commit>=3.0.0; extra == "dev"
Requires-Dist: build>=0.10.0; extra == "dev"
Requires-Dist: twine>=4.0.0; extra == "dev"
Requires-Dist: psutil>=5.9.0; extra == "dev"
Requires-Dist: pyyaml>=6.0.0; extra == "dev"
Requires-Dist: tomli>=2.0.0; extra == "dev"
Requires-Dist: packaging>=23.0; extra == "dev"
Dynamic: license-file
